LICENSE
README.md
setup.py
terraform_lxd_provider_wrapper.py
lib/terraform-provider-lxd_v1.5.0
terraform_lxd_provider_wrapper.egg-info/PKG-INFO
terraform_lxd_provider_wrapper.egg-info/SOURCES.txt
terraform_lxd_provider_wrapper.egg-info/dependency_links.txt
terraform_lxd_provider_wrapper.egg-info/entry_points.txt
terraform_lxd_provider_wrapper.egg-info/top_level.txt